app/__init__.py
app/extract_audio.py
extract_audio-0.32.dist-info/LICENSE.txt
extract_audio-0.32.dist-info/METADATA
extract_audio-0.32.dist-info/WHEEL
extract_audio-0.32.dist-info/entry_points.txt
extract_audio-0.32.dist-info/top_level.txt
extract_audio-0.32.dist-info/RECORD
