Metadata-Version: 2.1
Name: extract-audio
Version: 0.32
Summary: Extract audio from a directory of video files.
Home-page: https://github.com/zevaverbach/extract-audio
Author: Zev Averbach
Author-email: zev@averba.ch
License: UNKNOWN
Platform: UNKNOWN
License-File: LICENSE.txt
